dinuq/__init__.py
dinuq/checks.py
dinuq/make_ntcont.py
dinuq/rda.py
dinuq/rscu.py
dinuq/sdu.py
dinuq/sduc.py
dinuq/thedicts.py
dinuq-1.2.0.dist-info/LICENSE.txt
dinuq-1.2.0.dist-info/METADATA
dinuq-1.2.0.dist-info/WHEEL
dinuq-1.2.0.dist-info/top_level.txt
dinuq-1.2.0.dist-info/RECORD
