Metadata-Version: 2.1
Name: dinuq
Version: 1.2.0
Summary: The Dinucleotide Quantification Python package
Home-page: https://spyros-lytras.github.io/dinuq/
Download-URL: https://github.com/spyros-lytras/dinuq/dist/dinuq-1.2.0.tar
Author: Spyros Lytras
Author-email: s.lytras.1@research.gla.ac.uk
License: MIT
Project-URL: Documentation, https://spyros-lytras.github.io/dinuq/
Project-URL: CVR Bioinformatics, https://bioinformatics.cvr.ac.uk/
Keywords: bioinformatics dinucleotides viruses
Platform: UNKNOWN
Classifier: Intended Audience :: Science/Research
Classifier: Topic :: Scientific/Engineering :: Bio-Informatics
Classifier: Programming Language :: Python
Requires-Python: ~=3.6
License-File: LICENSE.txt
Requires-Dist: biopython
